{
  "name": "My Example Source",
  "subtitle": "A source for all of my apps",
  "description": "Welcome to my source! Here you'll find all of my apps.",
  "iconURL": "https://i.imgur.com/pqIZoZo.jpeg",
  "website": "https://altstudio.app",
  "patreonURL": "https://patreon.com/altstudio",
  "tintColor": "#6156e2",
  "featuredApps": [],
  "apps": [
    {
      "name": "Puppet War",
      "bundleIdentifier": "com.orenbentov.puppetwarfps",
      "marketplaceID": "",
      "developerName": "Example Developer",
      "subtitle": "An awesome app.",
      "localizedDescription": "This is an awesome app only available on AltStore.",
      "iconURL": "https://i.imgur.com/GAGgDT6.png",
      "tintColor": "#8404cc",
      "category": "other",
      "screenshots": [],
      "versions": [],
      "appPermissions": {
        "entitlements": [],
        "privacy": {}
      },
      "patreon": {}
    }
  ],
  "news": []
}